stemplates/__init__.py
stemplates/template_renderer.py
stemplates-1.0.0.dist-info/LICENSE
stemplates-1.0.0.dist-info/METADATA
stemplates-1.0.0.dist-info/WHEEL
stemplates-1.0.0.dist-info/top_level.txt
stemplates-1.0.0.dist-info/RECORD
